base_folder/__init__.py
base_folder/main.py
base_folder/analyser/__init__.py
base_folder/analyser/buses_in_districts.py
base_folder/analyser/punctuality.py
base_folder/analyser/transit_time.py
base_folder/analyser/velocity.py
base_folder/collecting_data/__init__.py
base_folder/collecting_data/bus_stops.py
base_folder/collecting_data/buses_locations.py
warsawbuses448378-0.0.1.dist-info/METADATA
warsawbuses448378-0.0.1.dist-info/WHEEL
warsawbuses448378-0.0.1.dist-info/top_level.txt
warsawbuses448378-0.0.1.dist-info/RECORD
